Workbook

Sheet Raw Data
A1: Order_ID | B1: Date | C1: Month | D1: Quarter | E1: Region | F1: State | G1: Category | H1: Sub_Category | I1: Product | J1: Sales_Rep | K1: Units | L1: Unit_Price | M1: Revenue | N1: COGS | O1: Gross_Profit | P1: Target
A2: ORD-1001 | B2: 2024-11-04 | C2: Nov | D2: Q4 | E2: North | F2: Minnesota | G2: Electronics | H2: Monitors | I2: Monitors | J2: James Liu | K2: 4 | L2: 259.81 | M2: 1039.24 | N2: 814.14 | O2: 225.1 | P2: 1207.87
A3: ORD-1002 | B3: 2024-10-14 | C3: Oct | D3: Q4 | E3: North | F3: Illinois | G3: Electronics | H3: Monitors | I3: Monitors | J3: Sarah Kim | K3: 20 | L3: 265.03 | M3: 5300.6 | N3: 3810.61 | O3: 1489.99 | P3: 4874.4
A4: ORD-1003 | B4: 2024-04-15 | C4: Apr | D4: Q2 | E4: East | F4: New York | G4: Electronics | H4: Headphones | I4: Headphones | J4: James Liu | K4: 5 | L4: 91.96 | M4: 459.8 | N4: 291.46 | O4: 168.34 | P4: 513.7
A5: ORD-1004 | B5: 2024-02-13 | C5: Feb | D5: Q1 | E5: North | F5: Minnesota | G5: Office Supply | H5: Folders | I5: Folders | J5: Sarah Kim | K5: 15 | L5: 9.55 | M5: 143.25 | N5: 45.16 | O5: 98.09 | P5: 170.55
A6: ORD-1005 | B6: 2024-02-18 | C6: Feb | D6: Q1 | E6: East | F6: New Jersey | G6: Furniture | H6: Chair | I6: Chair | J6: James Liu | K6: 2 | L6: 322.68 | M6: 645.36 | N6: 386.13 | O6: 259.23 | P6: 723.17
A7: ORD-1006 | B7: 2024-04-28 | C7: Apr | D7: Q2 | E7: North | F7: Michigan | G7: Office Supply | H7: Stapler | I7: Stapler | J7: Aisha Brown | K7: 12 | L7: 22.6 | M7: 271.2 | N7: 115.95 | O7: 155.25 | P7: 264.24
A8: ORD-1007 | B8: 2024-12-22 | C8: Dec | D8: Q4 | E8: North | F8: Wisconsin | G8: Furniture | H8: Chair | I8: Chair | J8: Carlos Ruiz | K8: 13 | L8: 289.13 | M8: 3758.69 | N8: 2413.18 | O8: 1345.51 | P8: 4412.28
A9: ORD-1008 | B9: 2024-11-11 | C9: Nov | D9: Q4 | E9: North | F9: Wisconsin | G9: Electronics | H9: Keyboards | I9: Keyboards | J9: Tom Kowalski | K9: 3 | L9: 53.91 | M9: 161.73 | N9: 87.4 | O9: 74.33 | P9: 190.84
A10: ORD-1009 | B10: 2024-04-21 | C10: Apr | D10: Q2 | E10: West | F10: Nevada | G10: Furniture | H10: Cabinet | I10: Cabinet | J10: Aisha Brown | K10: 5 | L10: 241.43 | M10: 1207.15 | N10: 779.73 | O10: 427.42 | P10: 1263.26
A11: ORD-1010 | B11: 2024-12-19 | C11: Dec | D11: Q4 | E11: West | F11: Nevada | G11: Office Supply | H11: Pens | I11: Pens | J11: Maria Santos | K11: 5 | L11: 13.19 | M11: 65.95 | N11: 20.02 | O11: 45.93 | P11: 58.16
A12: ORD-1011 | B12: 2024-02-05 | C12: Feb | D12: Q1 | E12: South | F12: Louisiana | G12: Furniture | H12: Desk | I12: Desk | J12: Maria Santos | K12: 20 | L12: 410.32 | M12: 8206.4 | N12: 5877.83 | O12: 2328.57 | P12: 8495.18
A13: ORD-1012 | B13: 2024-11-24 | C13: Nov | D13: Q4 | E13: North | F13: Minnesota | G13: Furniture | H13: Bookcase | I13: Bookcase | J13: Aisha Brown | K13: 14 | L13: 179.85 | M13: 2517.9 | N13: 1622.57 | O13: 895.33 | P13: 2143.07
... A501: ORD-1500 | B501: 2024-08-08 | C501: Aug | D501: Q3 | E501: West | F501: Nevada | G501: Electronics | H501: Headphones | I501: Headphones | J501: Maria Santos | K501: 13 | L501: 99.18 | M501: 1289.34 | N501: 788.7 | O501: 500.64 | P501: 1430.99

Sheet Pivot Summary
A3: Row Labels | B3: Sum of Revenue | C3: Sum of Target | D3: Sum of Attainment
A4: East | B4: 254684.84 | C4: 261163.91 | D4: 0.97519156
A5: North | B5: 192701.89 | C5: 196146.46 | D5: 0.98243879
A6: South | B6: 264706.55 | C6: 277527.02 | D6: 0.95380461
A7: West | B7: 261766.92 | C7: 266318.72 | D7: 0.98290845
A8: Grand Total | B8: 973860.2 | C8: 1001156.1 | D8: 0.97273561
A13: Row Labels | B13: Sum of Revenue | C13: Sum of Gross_Profit | D13: Margins %
A14: Electronics | B14: 448025.39 | C14: 113382.88 | D14: =GETPIVOTDATA("Sum of Gross_Profit",$A$13,"Category","Electronics")/GETPIVOTDATA("Sum of Revenue",$A$13,"Category","Electronics") -> 0.25307244
A15: Furniture | B15: 500895.86 | C15: 183350.41 | D15: =GETPIVOTDATA("Sum of Gross_Profit",$A$13,"Category","Furniture")/GETPIVOTDATA("Sum of Revenue",$A$13,"Category","Furniture") -> 0.36604497
A16: Office Supply | B16: 24938.95 | C16: 15015.13 | D16: =GETPIVOTDATA("Sum of Gross_Profit",$A$13,"Category","Office Supply")/GETPIVOTDATA("Sum of Revenue",$A$13,"Category","Office Supply") -> 0.60207547
A17: Grand Total | B17: 973860.2 | C17: 311748.42 | D17: =GETPIVOTDATA("Sum of Gross_Profit",$A$13)/GETPIVOTDATA("Sum of Revenue",$A$13) -> 0.32011619

Sheet Dashboard
A1: RETAIL SALES PERFORMANCE DASHBOARD | FY 2024
A3: Total Revenue | D3: Revenue Target | G3: Gross Profit | J3: Gross Margin % | M3: Target Attainment
S4: Monthly Revenue Trend 2024
A5: =SUM(GETPIVOTDATA("Sum of Revenue",'Pivot Summary'!$A$3)) -> 973860.2 | D5: =SUM(GETPIVOTDATA("Sum of Target",'Pivot Summary'!$A$3)) -> 1001156.1 | G5: =SUM(GETPIVOTDATA("Sum of Gross_Profit",'Pivot Summary'!$A$13)) -> 311748.42 | J5: =SUM('Pivot Summary'!D17) -> 0.32011619 | M5: =SUM(GETPIVOTDATA("Sum of Attainment",'Pivot Summary'!$A$3)) -> 0.97273561 | R5: Jan | S5: 77472.57
R6: Feb | S6: 68330.85
R7: Mar | S7: 94877.31
R8: Apr | S8: 76001.98
A9: Region | D9: Revenue | G9: Target | J9: Vs Target | M9: Attainment % | R9: May | S9: 110358.8
R10: Jun | S10: 72438.87
R11: Jul | S11: 79721.13
A12: North | D12: =SUMIF('Raw Data'!E:E,"North",'Raw Data'!M:M) -> 192701.89 | G12: =SUMIF('Raw Data'!E:E,"North",'Raw Data'!P:P) -> 196146.46 | J12: =GETPIVOTDATA("Sum of Revenue",'Pivot Summary'!$A$3,"Region","North")-GETPIVOTDATA("Sum of Target",'Pivot Summary'!$A$3,"Region","North") -> -3444.57 | M12: =GETPIVOTDATA("Sum of Revenue",'Pivot Summary'!$A$3,"Region","North")/GETPIVOTDATA("Sum of Target",'Pivot Summary'!$A$3,"Region","North") -> 0.98243879 | R12: Aug | S12: 79663.5
R13: Sep | S13: 81226.78
A14: South | D14: =SUMIF('Raw Data'!E:E,"South",'Raw Data'!M:M) -> 264706.55 | G14: =SUMIF('Raw Data'!E:E,"South",'Raw Data'!P:P) -> 277527.02 | J14: =GETPIVOTDATA("Sum of Revenue",'Pivot Summary'!$A$3,"Region","South")-GETPIVOTDATA("Sum of Target",'Pivot Summary'!$A$3,"Region","South") -> -12820.47 | M14: =GETPIVOTDATA("Sum of Attainment",'Pivot Summary'!$A$3,"Region","South") -> 0.95380461 | R14: Oct | S14: 87537.24
R15: Nov | S15: 85582.88
A16: East | D16: =SUMIF('Raw Data'!E:E,"East",'Raw Data'!M:M) -> 254684.84 | G16: =SUMIF('Raw Data'!E:E,"East",'Raw Data'!P:P) -> 261163.91 | J16: =GETPIVOTDATA("Sum of Revenue",'Pivot Summary'!$A$3,"Region","East")-GETPIVOTDATA("Sum of Target",'Pivot Summary'!$A$3,"Region","East") -> -6479.07 | M16: =GETPIVOTDATA("Sum of Attainment",'Pivot Summary'!$A$3,"Region","East") -> 0.97519156 | R16: Dec | S16: 60648.29
A18: West | D18: =SUMIF('Raw Data'!E:E,"West",'Raw Data'!M:M) -> 261766.92 | G18: =SUMIF('Raw Data'!E:E,"West",'Raw Data'!P:P) -> 266318.72 | J18: =GETPIVOTDATA("Sum of Revenue",'Pivot Summary'!$A$3,"Region","West")-GETPIVOTDATA("Sum of Target",'Pivot Summary'!$A$3,"Region","West") -> -4551.8 | M18: =GETPIVOTDATA("Sum of Attainment",'Pivot Summary'!$A$3,"Region","West") -> 0.98290845
A21: Category | D21: Revenue | G21: Gross Profit | J21: Margin %
O22: Key Insights & Recommendations
O23: 1. South region missed the target by about $12,820, which is the largest gap of any regions. A sales pipeline review is recommended for 2025.
A24: Electronics | D24: =SUMIF('Raw Data'!G:G,"Electronics",'Raw Data'!M:M) -> 448025.39 | G24: =GETPIVOTDATA("Sum of Gross_Profit",'Pivot Summary'!$A$13,"Category","Electronics") -> 113382.88 | J24: ='Pivot Summary'!D14 -> 0.25307244
O25: 2. Office supplies carries a 60% gross margin but only has a revenue of $24,939 and a gross profit of $15,015. The highest-margin category is significantly underutilized.
A26: Furniture | D26: =GETPIVOTDATA("Sum of Revenue",'Pivot Summary'!$A$13,"Category","Furniture") -> 500895.86 | G26: =GETPIVOTDATA("Sum of Gross_Profit",'Pivot Summary'!$A$13,"Category","Furniture") -> 183350.41 | J26: ='Pivot Summary'!D15 -> 0.36604497
O27: 3. Electronics generated $448k in revenue but only has a 25% margin. A pricing or vendor cost review could bring up profitability.
A28: Office Supplies | D28: =GETPIVOTDATA("Sum of Revenue",'Pivot Summary'!$A$13,"Category","Office Supply") -> 24938.95 | G28: =GETPIVOTDATA("Sum of Gross_Profit",'Pivot Summary'!$A$13,"Category","Office Supply") -> 15015.13 | J28: ='Pivot Summary'!D16 -> 0.60207547
O29: 4. December revenue fell to $60,468, the lowest month of the year, seasonal demand planning should account for Q4 softness
